src/__init__.py
src/bbox.py
src/bubble_clean.py
src/bubble_detect.py
src/config.py
src/console.py
src/draw_text.py
src/image_utils.py
src/main.py
src/manga_translate.py
src/ocr.py
src/output_manager.py
src/translate.py
src/fonts/CC Astro City Int Regular.ttf
src/fonts/__init__.py
manga_translator_cli-1.0.0.dist-info/METADATA
manga_translator_cli-1.0.0.dist-info/WHEEL
manga_translator_cli-1.0.0.dist-info/entry_points.txt
manga_translator_cli-1.0.0.dist-info/licenses/LICENSE.md
manga_translator_cli-1.0.0.dist-info/RECORD
