Metadata-Version: 2.4
Name: manga-translator-cli
Version: 1.0.0
Summary: A CLI tool for automatically translating manga pages from Japanese to English. Detects speech bubbles, extracts Japanese text using OCR, translates to English, and renders the translated text back onto images with proper alignment.
License-File: LICENSE.md
Requires-Python: >=3.13
Requires-Dist: accelerate>=1.12.0
Requires-Dist: ctranslate2>=4.6.3
Requires-Dist: einops>=0.8.1
Requires-Dist: huggingface-hub>=0.20.0
Requires-Dist: opencv-python>=4.8.0
Requires-Dist: pillow>=12.1.0
Requires-Dist: protobuf>=3.20.0
Requires-Dist: rich>=13.0.0
Requires-Dist: sentencepiece>=0.2.1
Requires-Dist: torch>=2.9.1
Requires-Dist: torchvision>=0.24.1
Requires-Dist: transformers==4.57.1
Requires-Dist: ultralytics>=8.0.0
